{"v":4,"entries":{"general-button--docs":{"id":"general-button--docs","title":"General/Button","name":"Docs","importPath":"./react-components/src/Button/stories/Button.stories.tsx","type":"docs","tags":["docs","autodocs"],"storiesImports":[]},"general-button--default":{"id":"general-button--default","title":"General/Button","name":"Default","importPath":"./react-components/src/Button/stories/Button.stories.tsx","tags":["story"],"type":"story"},"general-button--primary-color":{"id":"general-button--primary-color","title":"General/Button","name":"Color: Primary","importPath":"./react-components/src/Button/stories/Button.stories.tsx","tags":["story"],"type":"story"},"general-button--secondary-color":{"id":"general-button--secondary-color","title":"General/Button","name":"Color: Secondary","importPath":"./react-components/src/Button/stories/Button.stories.tsx","tags":["story"],"type":"story"},"general-button--ghost-color":{"id":"general-button--ghost-color","title":"General/Button","name":"Color: Ghost","importPath":"./react-components/src/Button/stories/Button.stories.tsx","tags":["story"],"type":"story"},"general-button--base-palette":{"id":"general-button--base-palette","title":"General/Button","name":"Palette: None","importPath":"./react-components/src/Button/stories/Button.stories.tsx","tags":["story"],"type":"story"},"general-button--green-palette":{"id":"general-button--green-palette","title":"General/Button","name":"Palette: Green","importPath":"./react-components/src/Button/stories/Button.stories.tsx","tags":["story"],"type":"story"},"general-button--yellow-palette":{"id":"general-button--yellow-palette","title":"General/Button","name":"Palette: Yellow","importPath":"./react-components/src/Button/stories/Button.stories.tsx","tags":["story"],"type":"story"},"general-button--red-palette":{"id":"general-button--red-palette","title":"General/Button","name":"Palette: Red","importPath":"./react-components/src/Button/stories/Button.stories.tsx","tags":["story"],"type":"story"},"general-button--brick-shape":{"id":"general-button--brick-shape","title":"General/Button","name":"Shape: Brick","importPath":"./react-components/src/Button/stories/Button.stories.tsx","tags":["story"],"type":"story"},"general-button--round-shape":{"id":"general-button--round-shape","title":"General/Button","name":"Shape: Round","importPath":"./react-components/src/Button/stories/Button.stories.tsx","tags":["story"],"type":"story"},"general-button--circle-shape":{"id":"general-button--circle-shape","title":"General/Button","name":"Shape: Circle","importPath":"./react-components/src/Button/stories/Button.stories.tsx","tags":["story"],"type":"story"},"general-typography-link--docs":{"id":"general-typography-link--docs","title":"General/Typography/Link","name":"Docs","importPath":"./react-components/src/Typography/stories/TypographyLink.stories.tsx","type":"docs","tags":["docs","autodocs"],"storiesImports":[]},"general-typography-link--default":{"id":"general-typography-link--default","title":"General/Typography/Link","name":"Default","importPath":"./react-components/src/Typography/stories/TypographyLink.stories.tsx","tags":["story"],"type":"story"},"general-typography-link--h-4":{"id":"general-typography-link--h-4","title":"General/Typography/Link","name":"Link: h4 font variant","importPath":"./react-components/src/Typography/stories/TypographyLink.stories.tsx","tags":["story"],"type":"story"},"general-typography-paragraph--docs":{"id":"general-typography-paragraph--docs","title":"General/Typography/Paragraph","name":"Docs","importPath":"./react-components/src/Typography/stories/TypographyParagraph.stories.tsx","type":"docs","tags":["docs","autodocs"],"storiesImports":[]},"general-typography-paragraph--default":{"id":"general-typography-paragraph--default","title":"General/Typography/Paragraph","name":"Default","importPath":"./react-components/src/Typography/stories/TypographyParagraph.stories.tsx","tags":["story"],"type":"story"},"general-typography-paragraph--h-4":{"id":"general-typography-paragraph--h-4","title":"General/Typography/Paragraph","name":"Paragraph: h4 font variant","importPath":"./react-components/src/Typography/stories/TypographyParagraph.stories.tsx","tags":["story"],"type":"story"},"general-typography-text--docs":{"id":"general-typography-text--docs","title":"General/Typography/Text","name":"Docs","importPath":"./react-components/src/Typography/stories/TypographyText.stories.tsx","type":"docs","tags":["docs","autodocs"],"storiesImports":[]},"general-typography-text--default":{"id":"general-typography-text--default","title":"General/Typography/Text","name":"Default","importPath":"./react-components/src/Typography/stories/TypographyText.stories.tsx","tags":["story"],"type":"story"},"general-typography-text--h-4":{"id":"general-typography-text--h-4","title":"General/Typography/Text","name":"Text: h4 font variant","importPath":"./react-components/src/Typography/stories/TypographyText.stories.tsx","tags":["story"],"type":"story"},"general-typography-title--docs":{"id":"general-typography-title--docs","title":"General/Typography/Title","name":"Docs","importPath":"./react-components/src/Typography/stories/TypographyTitle.stories.tsx","type":"docs","tags":["docs","autodocs"],"storiesImports":[]},"general-typography-title--default":{"id":"general-typography-title--default","title":"General/Typography/Title","name":"Default","importPath":"./react-components/src/Typography/stories/TypographyTitle.stories.tsx","tags":["story"],"type":"story"},"general-typography-title--h-2":{"id":"general-typography-title--h-2","title":"General/Typography/Title","name":"Heading: h2","importPath":"./react-components/src/Typography/stories/TypographyTitle.stories.tsx","tags":["story"],"type":"story"},"general-typography-title--h-3":{"id":"general-typography-title--h-3","title":"General/Typography/Title","name":"Heading: h3","importPath":"./react-components/src/Typography/stories/TypographyTitle.stories.tsx","tags":["story"],"type":"story"},"general-typography-title--h-4":{"id":"general-typography-title--h-4","title":"General/Typography/Title","name":"Heading: h4 with any font variant","importPath":"./react-components/src/Typography/stories/TypographyTitle.stories.tsx","tags":["story"],"type":"story"}}}
